opaiui/__init__.py
opaiui/app.py
opaiui/py.typed
opaiui-0.13.2.dist-info/METADATA
opaiui-0.13.2.dist-info/WHEEL
opaiui-0.13.2.dist-info/licenses/LICENSE
opaiui-0.13.2.dist-info/RECORD
