Metadata-Version: 2.4
Name: opaiui
Version: 0.13.2
Summary: Opinionated Pydantic.AI User Interface
Project-URL: Homepage, https://github.com/oneilsh/opaiui
Project-URL: Bug Tracker, https://github.com/oneilsh/opaiui/issues
Author-email: Shawn T O'Neil <oneilsh@gmail.com>
License-Expression: MIT
License-File: LICENSE
Classifier: License :: OSI Approved :: MIT License
Classifier: Operating System :: OS Independent
Classifier: Programming Language :: Python :: 3
Requires-Python: <4.0,>=3.10
Requires-Dist: dill<0.5.0,>=0.4.0
Requires-Dist: nest-asyncio<2.0.0,>=1.6.0
Requires-Dist: pydantic-ai>=0.4.0
Requires-Dist: python-dotenv>=1.1.1
Requires-Dist: streamlit>=1.46.1
Requires-Dist: upstash-redis>=1.4.0
